<?xml version="1.0" encoding="utf-8" ?>
<data>
	<description id="CT2 Map8 Enemies" />
	<spawnerDef name="mission8" />
	<wavesNumber limit="25" addPortion="0" />
	<difficulty initial="2" step="0.7" />
	<randomSeeds main="1275" support="642" champion="123323" boss="43411" />
	<supportWaves first="10" probability="0.5" />
	<bossWaves first="35" period="35" finalBoss="0" />
	<championWaves first="10" period="5" />
	
	<customWaves>
		<wave number="9" boss="0">
			<mainSquad actorName="unit" actorSubName="ninja" quantity="3" />
		</wave>
		<wave number="12" boss="0">
			<mainSquad actorName="unit" actorSubName="dendrologist" quantity="4" />
		</wave>
		<wave number="17" boss="0">
			<mainSquad actorName="unit" actorSubName="dendrologist" quantity="5" />
		</wave>
		<wave number="25" boss="0">
			<mainSquad actorName="unit" actorSubName="dendrologist" quantity="7" />
			<supportSquad actorName="unit" actorSubName="eagleDruid" quantity="2" />
		</wave>
	</customWaves>
	
</data>